<keymap version="1" name="IntelliJ IDEA Classic (OS X) copy" parent="Mac OS X">
  <action id="ActivateProjectToolWindow">
    <keyboard-shortcut first-keystroke="meta 1" />
    <keyboard-shortcut first-keystroke="ctrl p" />
  </action>
  <action id="CloseContent">
    <keyboard-shortcut first-keystroke="meta w" />
  </action>
  <action id="Console.TableResult.CompareCells" />
  <action id="Diff.ShowSettingsPopup" />
  <action id="EditorSelectWord">
    <keyboard-shortcut first-keystroke="ctrl w" />
  </action>
  <action id="GotoFile">
    <keyboard-shortcut first-keystroke="shift meta n" />
    <keyboard-shortcut first-keystroke="meta t" />
  </action>
  <action id="SelectNextOccurrence">
    <keyboard-shortcut first-keystroke="ctrl g" />
    <keyboard-shortcut first-keystroke="shift meta d" />
  </action>
  <action id="SplitVertically">
    <keyboard-shortcut first-keystroke="ctrl alt 2" />
  </action>
  <action id="Uml.ShowDiff" />
  <action id="Vcs.UpdateProject" />
</keymap>